Metadata-Version: 2.1
Name: odoo-addon-sale_order_invoicing_finished_task
Version: 18.0.1.0.0.2
Requires-Python: >=3.10
Requires-Dist: odoo==18.0.*
Summary: Control invoice order lines if their related task has been set to invoiceable
Home-page: https://github.com/OCA/sale-workflow
License: AGPL-3
Author: Tecnativa, Camptocamp, Odoo Community Association (OCA)
Author-email: support@odoo-community.org
Classifier: Programming Language :: Python
Classifier: Framework :: Odoo
Classifier: Framework :: Odoo :: 18.0
Classifier: License :: OSI Approved :: GNU Affero General Public License v3
